kubetpl/__init__.py
kubetpl/aws.py
kubetpl/gcp.py
kubetpl/kubetpl.py
kubetpl-1.2.30.dist-info/LICENSE
kubetpl-1.2.30.dist-info/METADATA
kubetpl-1.2.30.dist-info/WHEEL
kubetpl-1.2.30.dist-info/entry_points.txt
kubetpl-1.2.30.dist-info/top_level.txt
kubetpl-1.2.30.dist-info/RECORD
