Metadata-Version: 2.1
Name: kubetpl
Version: 1.2.30
Summary: A template tool for kubernetes resources
Home-page: https://github.com/grauerwf/kubetpl
Author: Grauer W01f
Author-email: grauerwf@gmail.com
Classifier: Development Status :: 3 - Alpha
Classifier: Intended Audience :: Developers
Classifier: Intended Audience :: System Administrators
Classifier: Programming Language :: Python :: 3
Classifier: License :: OSI Approved :: Apache Software License
Classifier: Operating System :: OS Independent
Requires-Python: >=3.6
License-File: LICENSE
Requires-Dist: Jinja2
Requires-Dist: PyYAML
Requires-Dist: boto3
Requires-Dist: google-cloud-secret-manager
